ibptws/config.py
ibptws/__init__.py
ibptws/servico.py
ibptws/excecoes.py
ibptws/produto.py
ibptws-0.1.dist-info/metadata.json
ibptws-0.1.dist-info/METADATA
ibptws-0.1.dist-info/RECORD
ibptws-0.1.dist-info/DESCRIPTION.rst
ibptws-0.1.dist-info/top_level.txt
ibptws-0.1.dist-info/WHEEL
